{
  "lastUpdatedBy": "cortechdigitallab@gmail.com",
  "lastUpdatedDate": "2023-12-23T07:24:17.133979416+08:00",
  "code": "860-417-852-718-703",
  "createdDate": "2023-12-23T07:24:17.133882375+08:00",
  "createdBy": "cortechdigitallab@gmail.com",
  "domain": "department",
  "name": "Department 860-417-852-718-703",
  "description": "Department 860-417-852-718-703 description",
  "id": "65861aa11f68a440e11de02b",
  "region": {
    "parent": {
      "lastUpdatedBy": "cortechdigitallab@gmail.com",
      "lastUpdatedDate": "2023-12-23T07:24:12.455679762+08:00",
      "code": "759-760-449-838-651",
      "createdDate": "2023-12-23T07:24:12.455614803+08:00",
      "createdBy": "cortechdigitallab@gmail.com",
      "domain": "region",
      "postalCode": 1,
      "name": "Province 759-760-449-838-651",
      "description": "Province 759-760-449-838-651 description",
      "id": "65861a9c1f68a440e11de029",
      "type": "PROVINCE"
    },
    "lastUpdatedBy": "cortechdigitallab@gmail.com",
    "lastUpdatedDate": "2023-12-23T07:24:14.384210263+08:00",
    "code": "5-766-89-680-341",
    "createdDate": "2023-12-23T07:24:14.384125388+08:00",
    "createdBy": "cortechdigitallab@gmail.com",
    "domain": "region",
    "postalCode": 11,
    "name": "City 5-766-89-680-341",
    "description": "City 5-766-89-680-341 description",
    "id": "65861a9e1f68a440e11de02a",
    "type": "CITY"
  }
}